kviz/__init__.py
kviz/visualizer.py
kviz-0.0.12.dist-info/LICENSE
kviz-0.0.12.dist-info/METADATA
kviz-0.0.12.dist-info/WHEEL
kviz-0.0.12.dist-info/top_level.txt
kviz-0.0.12.dist-info/RECORD
