Metadata-Version: 2.2
Name: kviz
Version: 0.0.12
Summary: A Library for visualizing keras neural networks
License: Apache License 2.0
Classifier: Programming Language :: Python :: 3.9
Requires-Python: >=3.9, <4
License-File: LICENSE
Requires-Dist: tensorflow
Requires-Dist: networkx
Requires-Dist: pygraphviz
Requires-Dist: matplotlib
Requires-Dist: imageio
Provides-Extra: test
Requires-Dist: pytest; extra == "test"
Requires-Dist: pytest-cov; extra == "test"
Requires-Dist: testfixtures; extra == "test"
Dynamic: classifier
Dynamic: description
Dynamic: description-content-type
Dynamic: license
Dynamic: provides-extra
Dynamic: requires-dist
Dynamic: requires-python
Dynamic: summary
